pytket_honeywell/__init__.py
pytket_honeywell-1.0.0.dist-info/LICENSE
pytket_honeywell-1.0.0.dist-info/WHEEL
pytket_honeywell-1.0.0.dist-info/METADATA
pytket_honeywell-1.0.0.dist-info/RECORD
