Metadata-Version: 2.1
Name: pytket-honeywell
Version: 1.0.0
Summary: pytket-honeywell
Author-email: Alec Edgington <alec.edgington@quantinuum.com>
Classifier: License :: OSI Approved :: Apache Software License
Project-URL: Home, https://cqcl.github.io/pytket-quantinuum/api/
